basicsoperations/__init__.py
basicsoperations/operations.py
basicsoperations-0.1.1.dist-info/LICENSE
basicsoperations-0.1.1.dist-info/METADATA
basicsoperations-0.1.1.dist-info/WHEEL
basicsoperations-0.1.1.dist-info/top_level.txt
basicsoperations-0.1.1.dist-info/RECORD
