Metadata-Version: 2.1
Name: basicsoperations
Version: 0.1.1
Summary: Uma biblioteca para cálculos básicos
Home-page: https://github.com/JoaoMarcos91/basicsoperations.git
Author: João Marcos Simon Paulini
Author-email: joaomarcospaulini@gmail.com
License: MIT
License-File: LICENSE
